cinnamon_core/__init__.py
cinnamon_core/core/__init__.py
cinnamon_core/core/component.py
cinnamon_core/core/configuration.py
cinnamon_core/core/data.py
cinnamon_core/core/registry.py
cinnamon_core/utility/__init__.py
cinnamon_core/utility/json_utility.py
cinnamon_core/utility/logging_utility.py
cinnamon_core/utility/pickle_utility.py
cinnamon_core/utility/printing_utility.py
cinnamon_core/utility/python_utility.py
cinnamon_core-0.1.dist-info/LICENSE
cinnamon_core-0.1.dist-info/METADATA
cinnamon_core-0.1.dist-info/WHEEL
cinnamon_core-0.1.dist-info/top_level.txt
cinnamon_core-0.1.dist-info/RECORD
