Metadata-Version: 2.1
Name: cinnamon-core
Version: 0.1
Summary: [Core Package] A simple high-level framework for research
Home-page: https://github.com/federicoruggeri/cinnamore_core
Author: Federico Ruggeri
Author-email: federico.ruggeri6@unibo.it
License: MIT
Project-URL: Bug Tracker, https://github.com/federicoruggeri/cinnamore_core/issues
Platform: UNKNOWN
Classifier: Programming Language :: Python :: 3
Classifier: Operating System :: OS Independent
Requires-Python: >=3.6
Requires-Dist: absl-py (==1.4.0)
Requires-Dist: cloudpickle (~=2.2.1)
Requires-Dist: numpy (~=1.21.6)
Requires-Dist: pandas (~=1.3.5)
Requires-Dist: pytest (==7.3.1)
Requires-Dist: setuptools (~=67.1.0)
Requires-Dist: simplejson (==3.18.3)
Requires-Dist: typeguard (==2.13.3)
Requires-Dist: networkx (~=2.6.3)
Requires-Dist: jsonpickle (~=3.0.1)
Requires-Dist: pyvis (~=0.3.2)
